runkmc/__init__.py
runkmc/cli.py
runkmc/build/RunKMC
runkmc/kmc/__init__.py
runkmc/kmc/config.py
runkmc/kmc/execution.py
runkmc/kmc/run.py
runkmc/models/__init__.py
runkmc/models/templates/binary/CRP1_Template.txt
runkmc/models/templates/binary/CRP3_Template.txt
runkmc/models/templates/binary/FRP2_Template.txt
runkmc/results/__init__.py
runkmc/results/paths.py
runkmc/results/polymers.py
runkmc/results/results.py
runkmc/results/state.py
runkmc/vis/__init__.py
runkmc/vis/conversion.py
runkmc/vis/polymers.py
runkmc.libs/libgcc_s-887de51c.so.1
runkmc.libs/libstdc++-d6415257.so.6.0.33
runkmc-0.1.1.dist-info/METADATA
runkmc-0.1.1.dist-info/WHEEL
runkmc-0.1.1.dist-info/entry_points.txt
runkmc-0.1.1.dist-info/top_level.txt
runkmc-0.1.1.dist-info/RECORD
runkmc-0.1.1.dist-info/licenses/LICENSE
