Metadata-Version: 2.4
Name: runkmc
Version: 0.1.1
Summary: Kinetic Monte Carlo Simulator for Polymerization
Author-email: Devon Callan <devoncallan@ucsb.edu>
Requires-Python: >=3.10
License-File: LICENSE
Requires-Dist: numpy
Requires-Dist: pandas
Requires-Dist: matplotlib
Requires-Dist: tqdm
Requires-Dist: pyyaml
Dynamic: license-file
